[{"message":"NOTIFICATION OF SUBSTANTIAL SHAREHOLDING","category":"FLAGGING","formatedDate":"19.12.2008"},{"message":"MELDING OM SIGNIFIKANT AKSJEPOST","category":"FLAGGING","formatedDate":"19.12.2008"},{"message":"Boring på Gita-prospektet i Danmark har startet","category":"ANDRE BØRSMELDINGER","formatedDate":"10.12.2008"},{"message":"Drilling on the Gita prospect in Denmark has started","category":"ANDRE BØRSMELDINGER","formatedDate":"10.12.2008"},{"message":"Noreco\u0027s financial calendar 2009","category":"FINANSIELL KALENDER","formatedDate":"10.12.2008"},{"message":"Norecos finansielle kalender 2009","category":"FINANSIELL KALENDER","formatedDate":"10.12.2008"},{"message":"Brage brønn testet mer enn 15 000 fat per dag","category":"ANDRE BØRSMELDINGER","formatedDate":"08.12.2008"},{"message":"Brage well tested more than 15 000 barrels per day","category":"ANDRE BØRSMELDINGER","formatedDate":"08.12.2008"},{"message":"Sterk produksjon i november","category":"ANDRE BØRSMELDINGER","formatedDate":"03.12.2008"},{"message":"Strong production in November","category":"ANDRE BØRSMELDINGER","formatedDate":"03.12.2008"},{"message":"Aksjekapitalforhøyelse","category":"ANDRE BØRSMELDINGER","formatedDate":"18.11.2008"},{"message":"Share capital increase","category":"ANDRE BØRSMELDINGER","formatedDate":"18.11.2008"},{"message":"Seks tildelinger til Noreco i 25. lisensrunde i Storbritania","category":"ANDRE BØRSMELDINGER","formatedDate":"13.11.2008"},{"message":"Six awards to Noreco in the UK 25th round","category":"ANDRE BØRSMELDINGER","formatedDate":"13.11.2008"},{"message":"Noreco fortsetter sitt porteføljeforvaltningsprogram","category":"ANDRE BØRSMELDINGER","formatedDate":"06.11.2008"},{"message":"Noreco continues portfolio management program","category":"ANDRE BØRSMELDINGER","formatedDate":"06.11.2008"},{"message":"Produksjon i oktober i tråd med økt guiding","category":"ANDRE BØRSMELDINGER","formatedDate":"05.11.2008"},{"message":"October production in line with increased guidance","category":"ANDRE BØRSMELDINGER","formatedDate":"05.11.2008"},{"message":"MELDING OM TRANSAKSJON I HENHOLD TIL VPHL. § 4-1","category":"MELDEPLIKTIG HANDEL","formatedDate":"04.11.2008"},{"message":"NOTIFICATION OF TRANSACTION PURSUANT TO SECTION 4-1 OF THE SECURITIES TRADING ACT","category":"MELDEPLIKTIG HANDEL","formatedDate":"04.11.2008"},{"message":"Godkjennelse av tidlig nedbetaling av NOK 560 millioner i obligasjoner og fjerning av lånerestriksjon","category":"OBLIGASJONSHENDELSER","formatedDate":"03.11.2008"},{"message":"Godkjennelse av tidlig nedbetaling av NOK 560 millioner i obligasjoner og fjerning av lånerestriksjon","category":"OBLIGASJONSHENDELSER","formatedDate":"03.11.2008"},{"message":"Godkjennelse av tidlig nedbetaling av NOK 560 millioner i obligasjoner og fjerning av lånerestriksjon","category":"OBLIGASJONSHENDELSER","formatedDate":"03.11.2008"},{"message":"NOK 560 million early redemption of bonds and deletion of bond covenant approved","category":"OBLIGASJONSHENDELSER","formatedDate":"03.11.2008"},{"message":"NOK 560 million early redemption of bonds and deletion of bond covenant approved","category":"OBLIGASJONSHENDELSER","formatedDate":"03.11.2008"},{"message":"NOK 560 million early redemption of bonds and deletion of bond covenant approved","category":"OBLIGASJONSHENDELSER","formatedDate":"03.11.2008"},{"message":"Notice from Bondholders` Meeting","category":"OBLIGASJONSHENDELSER","formatedDate":"03.11.2008"},{"message":"Notice from Bondholders` Meeting","category":"OBLIGASJONSHENDELSER","formatedDate":"03.11.2008"},{"message":"NOTIFICATION OF TRANSACTION PURSUANT TO SECTION 4-1 OF THE SECURITIES TRADING ACT","category":"MELDEPLIKTIG HANDEL","formatedDate":"24.10.2008"},{"message":"NOTIFICATION OF TRANSACTION PURSUANT TO SECTION 4-1 OF THE SECURITIES TRADING ACT","category":"MELDEPLIKTIG HANDEL","formatedDate":"24.10.2008"},{"message":"NOTIFICATION OF TRANSACTION PURSUANT TO SECTION 4-1 OF THE SECURITIES TRADING ACT","category":"MELDEPLIKTIG HANDEL","formatedDate":"23.10.2008"},{"message":"Noreco gjør nytt oljefunn","category":"ANDRE BØRSMELDINGER","formatedDate":"23.10.2008"},{"message":"Noreco makes new oil discovery","category":"ANDRE BØRSMELDINGER","formatedDate":"23.10.2008"},{"message":"Rekordresultat fra Noreco i 3.kv 2008","category":"FINANSIELL RAPPORTERING","formatedDate":"23.10.2008"},{"message":"Record results from Noreco in 3Q 2008","category":"FINANSIELL RAPPORTERING","formatedDate":"23.10.2008"},{"message":"Bondholders Meeting","category":"OBLIGASJONSHENDELSER","formatedDate":"22.10.2008"},{"message":"Bondholders Meeting","category":"OBLIGASJONSHENDELSER","formatedDate":"22.10.2008"},{"message":"Forslag om tidlig nedbetaling av NOK 560 millioner i obligasjoner og fjerning av lånerestriksjon","category":"OBLIGASJONSHENDELSER","formatedDate":"22.10.2008"},{"message":"Forslag om tidlig nedbetaling av NOK 560 millioner i obligasjoner og fjerning av lånerestriksjon","category":"OBLIGASJONSHENDELSER","formatedDate":"22.10.2008"},{"message":"Forslag om tidlig nedbetaling av NOK 560 millioner i obligasjoner og fjerning av lånerestriksjon","category":"OBLIGASJONSHENDELSER","formatedDate":"22.10.2008"},{"message":"Proposed NOK 560 million early redemption of bonds and deletion of bond covenant","category":"OBLIGASJONSHENDELSER","formatedDate":"22.10.2008"},{"message":"Proposed NOK 560 million early redemption of bonds and deletion of bond covenant","category":"OBLIGASJONSHENDELSER","formatedDate":"22.10.2008"},{"message":"Proposed NOK 560 million early redemption of bonds and deletion of bond covenant","category":"OBLIGASJONSHENDELSER","formatedDate":"22.10.2008"},{"message":"Invitasjon til Noreco 3. kv 08 presentasjon / webcast","category":"ANDRE BØRSMELDINGER","formatedDate":"15.10.2008"},{"message":"Invitation to Noreco Q3 08 Presentation / Webcast","category":"ANDRE BØRSMELDINGER","formatedDate":"15.10.2008"},{"message":"Mandatory notification of trade","category":"MELDEPLIKTIG HANDEL","formatedDate":"13.10.2008"},{"message":"Siri back in production today","category":"ANDRE BØRSMELDINGER","formatedDate":"09.10.2008"},{"message":"Siri tilbake i produksjon i dag","category":"ANDRE BØRSMELDINGER","formatedDate":"09.10.2008"},{"message":"Analytikertelefonkonferanse","category":"ANDRE BØRSMELDINGER","formatedDate":"08.10.2008"},{"message":"Analyst conference call","category":"ANDRE BØRSMELDINGER","formatedDate":"08.10.2008"},{"message":"Notification of substantial shareholding : Norwegian Energy Co AS","category":"FLAGGING","formatedDate":"07.10.2008"},{"message":"Høy produksjon i september og god kontantbeholdning","category":"ANDRE BØRSMELDINGER","formatedDate":"01.10.2008"},{"message":"Strong production in September and strong cash position","category":"ANDRE BØRSMELDINGER","formatedDate":"01.10.2008"},{"message":"Noreco tilbakeviser rykter","category":"ANDRE BØRSMELDINGER","formatedDate":"30.09.2008"},{"message":"Noreco rejects rumours","category":"ANDRE BØRSMELDINGER","formatedDate":"30.09.2008"},{"message":"Noreco Presentasjon: Pareto Securities 15th annual Oil and Offshore Conference 10 Sept 2008","category":"ANDRE BØRSMELDINGER","formatedDate":"10.09.2008"},{"message":"Noreco Presentation: Pareto Securities 15th annual Oil and Offshore Conference 10 Sept 2008","category":"ANDRE BØRSMELDINGER","formatedDate":"10.09.2008"},{"message":"Strong production in August","category":"ANDRE BØRSMELDINGER","formatedDate":"03.09.2008"},{"message":"Sterk produksjon i august","category":"ANDRE BØRSMELDINGER","formatedDate":"03.09.2008"},{"message":"Huntingtonutbyggingen skrider fremover","category":"ANDRE BØRSMELDINGER","formatedDate":"27.08.2008"},{"message":"Huntington development moves forward","category":"ANDRE BØRSMELDINGER","formatedDate":"27.08.2008"},{"message":"Noreco fortsetter sitt porteføljeforvaltningsprogram","category":"ANDRE BØRSMELDINGER","formatedDate":"26.08.2008"},{"message":"Noreco continues portfolio management program","category":"ANDRE BØRSMELDINGER","formatedDate":"26.08.2008"},{"message":"Oppdatert firmaattest","category":"ANDRE BØRSMELDINGER","formatedDate":"21.08.2008"},{"message":"New Certificate of Registration","category":"ANDRE BØRSMELDINGER","formatedDate":"21.08.2008"},{"message":"Notification of Trade in Noreco","category":"MELDEPLIKTIG HANDEL","formatedDate":"20.08.2008"},{"message":"Nytt oljefunn for Noreco","category":"ANDRE BØRSMELDINGER","formatedDate":"20.08.2008"},{"message":"New oil discovery for Noreco","category":"ANDRE BØRSMELDINGER","formatedDate":"20.08.2008"},{"message":"Noreco gjør oljefunn i Danmark","category":"ANDRE BØRSMELDINGER","formatedDate":"08.08.2008"},{"message":"Noreco makes oil discovery in Denmark","category":"ANDRE BØRSMELDINGER","formatedDate":"08.08.2008"},{"message":"Rekordproduksjon i juli","category":"ANDRE BØRSMELDINGER","formatedDate":"04.08.2008"},{"message":"Record production in July","category":"ANDRE BØRSMELDINGER","formatedDate":"04.08.2008"},{"message":"NOTIFICATION OF SUBSTANTIAL SHAREHOLDING","category":"FLAGGING","formatedDate":"30.07.2008"},{"message":"Noreco øker produksjonmål for 2008","category":"ANDRE BØRSMELDINGER","formatedDate":"24.07.2008"},{"message":"Noreco increases 2008 production target","category":"ANDRE BØRSMELDINGER","formatedDate":"24.07.2008"},{"message":"Noreco 2.kv. 2008 - Sterkeste kvartal i selskapets historie","category":"FINANSIELL RAPPORTERING","formatedDate":"24.07.2008"},{"message":"Noreco Q2 2008 - The strongest quarter in the company\u0027s histrory","category":"FINANSIELL RAPPORTERING","formatedDate":"24.07.2008"},{"message":"Invitasjon til Noreco 2. kv 08 presentasjon / webcast","category":"ANDRE BØRSMELDINGER","formatedDate":"14.07.2008"},{"message":"Invitation to Noreco Q2 08 Presentation / Webcast","category":"ANDRE BØRSMELDINGER","formatedDate":"14.07.2008"},{"message":"Ny rente","category":"OBLIGASJONSHENDELSER","formatedDate":"10.07.2008"},{"message":"Noreco - Share Capital Increase","category":"ANDRE BØRSMELDINGER","formatedDate":"09.07.2008"},{"message":"Kapitalforhøyelse - Noreco","category":"ANDRE BØRSMELDINGER","formatedDate":"09.07.2008"},{"message":"NOTIFICATION OF TRANSACTION PURSUANT TO SECTION 4-1 OF THE SECURITIES TRADING ACT","category":"MELDEPLIKTIG HANDEL","formatedDate":"09.07.2008"},{"message":"Correction: NOTIFICATION OF TRANSACTION PURSUANT TO SECTION 4-1 OF THE SECURITIES TRADING ACT","category":"MELDEPLIKTIG HANDEL","formatedDate":"08.07.2008"},{"message":"NOTIFICATION OF TRANSACTION PURSUANT TO SECTION 4-1 OF THE SECURITIES TRADING ACT","category":"MELDEPLIKTIG HANDEL","formatedDate":"08.07.2008"},{"message":"Produksjon juni og 2.kv","category":"ANDRE BØRSMELDINGER","formatedDate":"03.07.2008"},{"message":"June and 2Q production","category":"ANDRE BØRSMELDINGER","formatedDate":"03.07.2008"},{"message":"Avsluttet frivillig tilbud til eiere av 6% Norwegian Energy Company ASA Senior Unsecured Convertible Bond Issue 2007/12 (ISIN NO 001036883.0)","category":"ANDRE BØRSMELDINGER","formatedDate":"03.07.2008"},{"message":"Completed tender offer to holders of 6% Norwegian Energy Company ASA Senior Unsecured Convertible Bond Issue 2007/12 (ISIN NO 001036883.0)","category":"ANDRE BØRSMELDINGER","formatedDate":"03.07.2008"},{"message":"Preliminary well results on Ipswich","category":"ANDRE BØRSMELDINGER","formatedDate":"30.06.2008"},{"message":"Foreløpig resultat av Ipswichbrønnen","category":"ANDRE BØRSMELDINGER","formatedDate":"30.06.2008"},{"message":"Frivillig tilbud til eiere av 6% Norwegian Energy Company ASA Senior Unsecured Convertible Bond Issue 2007/12 (ISIN NO 001036883.0)","category":"ANDRE BØRSMELDINGER","formatedDate":"30.06.2008"},{"message":"Tender offer to holders of 6% Norwegian Energy Company ASA Senior Unsecured Convertible Bond Issue 2007/12 (ISIN NO 001036883.0)","category":"ANDRE BØRSMELDINGER","formatedDate":"30.06.2008"},{"message":"Aksjekapitalforhøyelse","category":"ANDRE BØRSMELDINGER","formatedDate":"26.06.2008"},{"message":"Share capital increase","category":"ANDRE BØRSMELDINGER","formatedDate":"26.06.2008"},{"message":"Boreoppdatering","category":"ANDRE BØRSMELDINGER","formatedDate":"25.06.2008"},{"message":"Drilling update","category":"ANDRE BØRSMELDINGER","formatedDate":"25.06.2008"},{"message":"Nedbetaling Geopard obligasjonslån","category":"OBLIGASJONSHENDELSER","formatedDate":"23.06.2008"},{"message":"Full repayment Geopard Bond","category":"OBLIGASJONSHENDELSER","formatedDate":"23.06.2008"},{"message":"NOTIFICATION OF TRANSACTION","category":"MELDEPLIKTIG HANDEL","formatedDate":"19.06.2008"},{"message":"NOTIFICATION OF TRANSACTION","category":"MELDEPLIKTIG HANDEL","formatedDate":"19.06.2008"},{"message":"Noreco fullfører oppkjøpet av Talisman Oil Denmark Limited","category":"OPPKJØP","formatedDate":"19.06.2008"},{"message":"Noreco completes acquisition of Talisman Oil Denmark Limited","category":"OPPKJØP","formatedDate":"19.06.2008"},{"message":"Mandatory notification of trade","category":"MELDEPLIKTIG HANDEL","formatedDate":"19.06.2008"},{"message":"Subsequent offering allocation","category":"KAPITALENDRINGER / UTBY...","formatedDate":"17.06.2008"},{"message":"Tildeling i etterfølgende emisjon","category":"KAPITALENDRINGER / UTBY...","formatedDate":"17.06.2008"},{"message":"Endelig avtale for reservebasert lån og ny oljeprissikring","category":"ANDRE BØRSMELDINGER","formatedDate":"17.06.2008"},{"message":"Final reserve based lending agreement and new price hedging","category":"ANDRE BØRSMELDINGER","formatedDate":"17.06.2008"},{"message":"Subsequent offering completed","category":"PROSPEKT","formatedDate":"16.06.2008"},{"message":"Etterfølgende emisjon gjennomført","category":"PROSPEKT","formatedDate":"16.06.2008"},{"message":"NOTIFICATION OF TRANSACTION","category":"MELDEPLIKTIG HANDEL","formatedDate":"16.06.2008"},{"message":"Noreco bekrefter gassfunn","category":"ANDRE BØRSMELDINGER","formatedDate":"16.06.2008"},{"message":"Noreco confirms gas discovery","category":"ANDRE BØRSMELDINGER","formatedDate":"16.06.2008"},{"message":"NOTIFICATION OF SUBSTANTIAL SHAREHOLDING","category":"FLAGGING","formatedDate":"13.06.2008"},{"message":"NOTIFICATION OF SUBSTANTIAL SHAREHOLDING","category":"FLAGGING","formatedDate":"13.06.2008"},{"message":"NOTIFICATION OF TRANSACTION","category":"MELDEPLIKTIG HANDEL","formatedDate":"11.06.2008"},{"message":"NOTIFICATION OF TRANSACTION","category":"MELDEPLIKTIG HANDEL","formatedDate":"05.06.2008"},{"message":"Produksjon mai 2008","category":"ANDRE BØRSMELDINGER","formatedDate":"04.06.2008"},{"message":"May 2008 production","category":"ANDRE BØRSMELDINGER","formatedDate":"04.06.2008"},{"message":"NOTIFICATION OF TRANSACTION PURSUANT TO SECTION 4-1 OF THE SECURITIES TRADING ACT","category":"MELDEPLIKTIG HANDEL","formatedDate":"04.06.2008"},{"message":"Notification of trade","category":"MELDEPLIKTIG HANDEL","formatedDate":"03.06.2008"},{"message":"Mandatory notification of trade","category":"MELDEPLIKTIG HANDEL","formatedDate":"02.06.2008"},{"message":"NOTIFICATION OF TRANSACTION PURSUANT TO SECTION 4-1 OF THE SECURITIES TRADING ACT","category":"MELDEPLIKTIG HANDEL","formatedDate":"30.05.2008"},{"message":"Etterfølgende emisjon","category":"PROSPEKT","formatedDate":"28.05.2008"},{"message":"Subsequent offering","category":"PROSPEKT","formatedDate":"28.05.2008"},{"message":"Approved prospectus","category":"PROSPEKT","formatedDate":"28.05.2008"},{"message":"Noreco bygger ut Nini Øst-feltet","category":"ANDRE BØRSMELDINGER","formatedDate":"26.05.2008"},{"message":"Noreco develops the Nini East field","category":"ANDRE BØRSMELDINGER","formatedDate":"26.05.2008"},{"message":"Noreco acquires license in Norway","category":"ANDRE BØRSMELDINGER","formatedDate":"23.05.2008"},{"message":"Noreco øker eierandel i norsk lisens","category":"ANDRE BØRSMELDINGER","formatedDate":"23.05.2008"},{"message":"Noreco søker i 25. lisensrunde i Storbritania","category":"ANDRE BØRSMELDINGER","formatedDate":"21.05.2008"},{"message":"Noreco applies for licenses in the UK 25th round","category":"ANDRE BØRSMELDINGER","formatedDate":"21.05.2008"},{"message":"Noreco makes gas discovery","category":"ANDRE BØRSMELDINGER","formatedDate":"21.05.2008"},{"message":"Noreco gjør gassfunn","category":"ANDRE BØRSMELDINGER","formatedDate":"21.05.2008"},{"message":"Term Sheet for reservebasert lånefasilitet","category":"ANDRE BØRSMELDINGER","formatedDate":"09.05.2008"},{"message":"Term sheet reserve based lending facility","category":"ANDRE BØRSMELDINGER","formatedDate":"09.05.2008"},{"message":"Innløsning av obligasjonslån","category":"ANDRE BØRSMELDINGER","formatedDate":"09.05.2008"},{"message":"Repayment of bond","category":"ANDRE BØRSMELDINGER","formatedDate":"09.05.2008"},{"message":"Oppdatert firmaattest","category":"ANDRE BØRSMELDINGER","formatedDate":"07.05.2008"},{"message":"New Certificate of Registration","category":"ANDRE BØRSMELDINGER","formatedDate":"07.05.2008"},{"message":"Aksjekapitalforhøyelse","category":"KAPITALENDRINGER / UTBY...","formatedDate":"06.05.2008"},{"message":"Share capital increase","category":"KAPITALENDRINGER / UTBY...","formatedDate":"06.05.2008"},{"message":"April production","category":"ANDRE BØRSMELDINGER","formatedDate":"06.05.2008"},{"message":"Produksjon april 2008","category":"ANDRE BØRSMELDINGER","formatedDate":"06.05.2008"},{"message":"Noreco gjennomfører oppkjøp av danske lisenser fra Chevron","category":"ANDRE BØRSMELDINGER","formatedDate":"30.04.2008"},{"message":"Noreco completes acquisition of Danish licenses from Chevron","category":"ANDRE BØRSMELDINGER","formatedDate":"30.04.2008"},{"message":"Resultat fra boring av Yoda prospektet","category":"ANDRE BØRSMELDINGER","formatedDate":"30.04.2008"},{"message":"Drilling result of Yoda well","category":"ANDRE BØRSMELDINGER","formatedDate":"30.04.2008"},{"message":"DISCLOSURE OF SHAREHOLDING IN NORWEGIAN ENERGY COMPANY ASA","category":"FLAGGING","formatedDate":"28.04.2008"},{"message":"Meldepliktig handel","category":"MELDEPLIKTIG HANDEL","formatedDate":"28.04.2008"},{"message":"Notifiable trading","category":"MELDEPLIKTIG HANDEL","formatedDate":"28.04.2008"},{"message":"Planlagt etterfølgende emisjon","category":"KAPITALENDRINGER / UTBY...","formatedDate":"28.04.2008"},{"message":"Planned Subsequent Offering","category":"KAPITALENDRINGER / UTBY...","formatedDate":"28.04.2008"},{"message":"NORWEGIAN ENERGY COMPANY DISCLOSURE OF LARGE SHAREHOLDINGS","category":"FLAGGING","formatedDate":"28.04.2008"},{"message":"Gjennomført rettet emisjon og planlagt etterfølgende tilbud om tegning av aksjer","category":"KAPITALENDRINGER / UTBY...","formatedDate":"28.04.2008"},{"message":"Completed Private Placement and planned Subsequent Offering","category":"KAPITALENDRINGER / UTBY...","formatedDate":"28.04.2008"},{"message":"Protokoll fra ordinær generalforsamling","category":"GENERALFORSAMLINGSINFO","formatedDate":"25.04.2008"},{"message":"Minutes from Annual General Meeting","category":"GENERALFORSAMLINGSINFO","formatedDate":"25.04.2008"},{"message":"Rettet emisjon","category":"KAPITALENDRINGER / UTBY...","formatedDate":"25.04.2008"},{"message":"Private Placement","category":"KAPITALENDRINGER / UTBY...","formatedDate":"25.04.2008"},{"message":"Noreco kjøper Talisman Oil Denmark Limited","category":"OPPKJØP","formatedDate":"25.04.2008"},{"message":"Noreco acquires Talisman Oil Denmark Limited","category":"OPPKJØP","formatedDate":"25.04.2008"},{"message":"Noreco 1kv 08 - Sterkt driftsresultat","category":"FINANSIELL RAPPORTERING","formatedDate":"24.04.2008"},{"message":"Noreco Q1 08 - Strong operating results in Q1 08","category":"FINANSIELL RAPPORTERING","formatedDate":"24.04.2008"},{"message":"Årlig oversikt","category":"ÅRSOVERSIKT","formatedDate":"16.04.2008"},{"message":"Annual overview","category":"ÅRSOVERSIKT","formatedDate":"16.04.2008"},{"message":"Noreco selger andel i sør-øst Tor","category":"ANDRE BØRSMELDINGER","formatedDate":"14.04.2008"},{"message":"Noreco sells South East Tor share","category":"ANDRE BØRSMELDINGER","formatedDate":"14.04.2008"},{"message":"Noreco - Annual reserve statement 2007","category":"PETROLEUM RESERVER","formatedDate":"11.04.2008"},{"message":"Noreco - Årlig reserverapport for 2007","category":"PETROLEUM RESERVER","formatedDate":"11.04.2008"},{"message":"Noreco publishes annual report for 2007","category":"FINANSIELL RAPPORTERING","formatedDate":"11.04.2008"},{"message":"Noreco publiserer årsrapport for 2007","category":"FINANSIELL RAPPORTERING","formatedDate":"11.04.2008"},{"message":"Noreco presentasjon First Securities Energy Summit, London.","category":"ANDRE BØRSMELDINGER","formatedDate":"08.04.2008"},{"message":"Noreco presentation at First Securities Energy Summit, London","category":"ANDRE BØRSMELDINGER","formatedDate":"08.04.2008"},{"message":"Innkalling til generalforsamling","category":"GENERALFORSAMLINGSINFO","formatedDate":"04.04.2008"},{"message":"Call for annual general meeting","category":"GENERALFORSAMLINGSINFO","formatedDate":"04.04.2008"},{"message":"Produksjon mars 2008","category":"ANDRE BØRSMELDINGER","formatedDate":"01.04.2008"},{"message":"March 2008 Production","category":"ANDRE BØRSMELDINGER","formatedDate":"01.04.2008"},{"message":"Noreco board approves 2007 annual report","category":"FINANSIELL RAPPORTERING","formatedDate":"31.03.2008"},{"message":"Selskapspresentasjon","category":"ANDRE BØRSMELDINGER","formatedDate":"11.03.2008"},{"message":"Company Presentation","category":"ANDRE BØRSMELDINGER","formatedDate":"11.03.2008"},{"message":"Ny firmaattest","category":"ANDRE BØRSMELDINGER","formatedDate":"11.03.2008"},{"message":"New company certificate","category":"ANDRE BØRSMELDINGER","formatedDate":"11.03.2008"},{"message":"Produksjon februar 2008","category":"ANDRE BØRSMELDINGER","formatedDate":"05.03.2008"},{"message":"February 2008 production","category":"ANDRE BØRSMELDINGER","formatedDate":"05.03.2008"},{"message":"Nedsalg i letelisenser","category":"ANDRE BØRSMELDINGER","formatedDate":"27.02.2008"},{"message":"Farm-down of exploration licenses","category":"ANDRE BØRSMELDINGER","formatedDate":"27.02.2008"},{"message":"Noreco - Brage well tested more than 17 000 barrels per day","category":"ANDRE BØRSMELDINGER","formatedDate":"25.02.2008"},{"message":"Noreco - Brage brønn testet mer enn 17 000 fat per dag","category":"ANDRE BØRSMELDINGER","formatedDate":"25.02.2008"},{"message":"Mandatory Notification of Trade","category":"MELDEPLIKTIG HANDEL","formatedDate":"22.02.2008"},{"message":"Noreco - Aksjekapitalforhøyelse","category":"ANDRE BØRSMELDINGER","formatedDate":"19.02.2008"},{"message":"Noreco - Registered share capital increase","category":"ANDRE BØRSMELDINGER","formatedDate":"19.02.2008"},{"message":"Vellykket avgrensningsbrønn på Nemo","category":"ANDRE BØRSMELDINGER","formatedDate":"15.02.2008"},{"message":"Successful Nemo appraisal well","category":"ANDRE BØRSMELDINGER","formatedDate":"15.02.2008"},{"message":"Noreco 4kv 07 - Sterkt driftsresultat","category":"FINANSIELL RAPPORTERING","formatedDate":"14.02.2008"},{"message":"Noreco Q4 07 - Strong operating result","category":"FINANSIELL RAPPORTERING","formatedDate":"14.02.2008"},{"message":"Noreco presenterer planene for 2008","category":"ANDRE BØRSMELDINGER","formatedDate":"14.02.2008"},{"message":"Noreco outlines plans for 2008","category":"ANDRE BØRSMELDINGER","formatedDate":"14.02.2008"},{"message":"Første fase av avgrensning av Huntington-funnet avsluttet","category":"ANDRE BØRSMELDINGER","formatedDate":"11.02.2008"},{"message":"First phase of appraisal of the Huntington discovery completed","category":"ANDRE BØRSMELDINGER","formatedDate":"11.02.2008"},{"message":"Stor tildeling til Noreco i APA 2007","category":"ANDRE BØRSMELDINGER","formatedDate":"08.02.2008"},{"message":"Large award to Noreco in APA 2007","category":"ANDRE BØRSMELDINGER","formatedDate":"08.02.2008"},{"message":"Noreco - Produksjon januar 2008","category":"ANDRE BØRSMELDINGER","formatedDate":"08.02.2008"},{"message":"Noreco - January 2008 production","category":"ANDRE BØRSMELDINGER","formatedDate":"08.02.2008"},{"message":"Noreco - Vellykket avgrensningsbrønn på Oselvar","category":"ANDRE BØRSMELDINGER","formatedDate":"08.02.2008"},{"message":"Noreco - Successful Oselvar appraisal well","category":"ANDRE BØRSMELDINGER","formatedDate":"08.02.2008"},{"message":"Låneavtale underbygger leteprogram i 2008 og 2009","category":"AVTALER","formatedDate":"04.02.2008"},{"message":"Loan facility underpins 2008 and 2009 exploration and appraisal activities","category":"AVTALER","formatedDate":"04.02.2008"},{"message":"NOTIFICATION OF TRANSACTION PURSUANT TO SECTION 3-1 OF THE SECURITIES TRADING ACT","category":"MELDEPLIKTIG HANDEL","formatedDate":"29.01.2008"},{"message":"Transaction of close Associate- Noreco (NOR)","category":"MELDEPLIKTIG HANDEL","formatedDate":"24.01.2008"},{"message":"Mandatory notification of trade","category":"MELDEPLIKTIG HANDEL","formatedDate":"17.01.2008"},{"message":"Mandatory notification of trade","category":"MELDEPLIKTIG HANDEL","formatedDate":"17.01.2008"},{"message":"Mandatory notification of trade","category":"MELDEPLIKTIG HANDEL","formatedDate":"17.01.2008"},{"message":"Mandatory notification of trades","category":"MELDEPLIKTIG HANDEL","formatedDate":"16.01.2008"},{"message":"Mandatory notification of trade","category":"MELDEPLIKTIG HANDEL","formatedDate":"16.01.2008"},{"message":"Mandatory notification of trade","category":"MELDEPLIKTIG HANDEL","formatedDate":"16.01.2008"},{"message":"Noreco - Share capital increase","category":"KAPITALENDRINGER / UTBY...","formatedDate":"16.01.2008"},{"message":"Mandatory notification of trade","category":"MELDEPLIKTIG HANDEL","formatedDate":"14.01.2008"},{"message":"Mandatory notification of trade","category":"MELDEPLIKTIG HANDEL","formatedDate":"14.01.2008"},{"message":"Noreco - Protokoll fra ekstraordinær generalforsamling","category":"GENERALFORSAMLINGSINFO","formatedDate":"14.01.2008"},{"message":"Noreco - Minutes from Extraordinary General Meeting","category":"GENERALFORSAMLINGSINFO","formatedDate":"14.01.2008"},{"message":"Ny rente","category":"OBLIGASJONSHENDELSER","formatedDate":"10.01.2008"},{"message":"Noreco - December and 4Q 2007 production","category":"ANDRE BØRSMELDINGER","formatedDate":"10.01.2008"},{"message":"NORECO Company presentation","category":"ANDRE BØRSMELDINGER","formatedDate":"09.01.2008"},{"message":"NORECO - Oselvar well confirms good reservoir characteristics","category":"ANDRE BØRSMELDINGER","formatedDate":"04.01.2008"},{"message":"CALLING NOTICE FOR EXTRAORDINARY GENERAL MEETING","category":"GENERALFORSAMLINGSINFO","formatedDate":"20.12.2007"},{"message":"INNKALLING TIL EKSTRAORDINÆR GENERALFORSAMLING","category":"GENERALFORSAMLINGSINFO","formatedDate":"20.12.2007"},{"message":"NEMO APPRAISAL WELL SPUDDED","category":"ANDRE BØRSMELDINGER","formatedDate":"17.12.2007"},{"message":"CORR * COMPLETION OF FIRST STAGE OF APPRAISAL DRILLING ON HUNGTIONTON DI","category":"ANDRE BØRSMELDINGER","formatedDate":"14.12.2007"},{"message":"COMPLETION OF FIRST STAGE OF APPRAISAL DRILLING ON HUNGTIONTON DISCOVERY","category":"ANDRE BØRSMELDINGER","formatedDate":"14.12.2007"},{"message":"FINANCIAL CALENDAR 2008","category":"FINANSIELL KALENDER","formatedDate":"07.12.2007"},{"message":"NOVEMBER 2007 PRODUCTION","category":"ANDRE BØRSMELDINGER","formatedDate":"06.12.2007"},{"message":"REGISTERED SHARE CAPITAL INCREASE","category":"KAPITALENDRINGER / UTBY...","formatedDate":"04.12.2007"},{"message":"EXPLORATION FINANCING FACILITY","category":"AVTALER","formatedDate":"28.11.2007"},{"message":"NORECO Q3 07 - CONTINUED STRONG GROWTH","category":"FINANSIELL RAPPORTERING","formatedDate":"23.11.2007"},{"message":"NORECO 3.KV 07 - FORTSATT STERK VEKST","category":"FINANSIELL RAPPORTERING","formatedDate":"23.11.2007"},{"message":"NORECO ASA - SHARE CAPITAL INCREASE","category":"KAPITALENDRINGER / UTBY...","formatedDate":"21.11.2007"},{"message":"OCTOBER 2007 PRODUCTION","category":"ANDRE BØRSMELDINGER","formatedDate":"14.11.2007"},{"message":"Q3 2007 PRESENTATION","category":"FINANSIELL KALENDER","formatedDate":"13.11.2007"},{"message":"NORECO EXITS OMAN AND GERMANY","category":"AVTALER","formatedDate":"09.11.2007"},{"message":"OSLO BØRS - NOR - NEW SECURITY AS FROM TODAY","category":"NOTERING AV VERDIPAPIRE...","formatedDate":"09.11.2007"},{"message":"OSLO BØRS - NOR - NYTT SELSKAP TIL NOTERING I DAG","category":"NOTERING AV VERDIPAPIRE...","formatedDate":"09.11.2007"},{"message":"OSLO BØRS - NOR - NEW SECURITY AS FROM TOMORROW","category":"NOTERING AV VERDIPAPIRE...","formatedDate":"08.11.2007"},{"message":"OSLO BØRS - NOR - NYTT SELSKAP TIL NOTERING I MORGEN","category":"NOTERING AV VERDIPAPIRE...","formatedDate":"08.11.2007"},{"message":"OSLO BØRS - NYTT LÅN TIL NOTERING I DAG**KORR","category":"NOTERING AV VERDIPAPIRE...","formatedDate":"06.11.2007"},{"message":"OSLO BØRS - NYTT LÅN TIL NOTERING I DAG**KORR","category":"NOTERING AV VERDIPAPIRE...","formatedDate":"06.11.2007"},{"message":"OSLO BØRS - NYTT LÅN TIL NOTERING I DAG","category":"NOTERING AV VERDIPAPIRE...","formatedDate":"06.11.2007"},{"message":"OSLO BØRS - NYTT LÅN TIL NOTERING I DAG","category":"NOTERING AV VERDIPAPIRE...","formatedDate":"06.11.2007"},{"message":"OSLO BØRS - NOR02 - NYTT LÅN TIL NOTERING I MORGEN","category":"NOTERING AV VERDIPAPIRE...","formatedDate":"05.11.2007"},{"message":"OSLO BØRS - NOR01 - NYTT LÅN TIL NOTERING I MORGEN","category":"NOTERING AV VERDIPAPIRE...","formatedDate":"05.11.2007"},{"message":"LISTING OF NORWEGIAN ENERGY COMPANY ASA ON OSLO BØRS","category":"ANDRE BØRSMELDINGER","formatedDate":"02.11.2007"},{"message":"APPROVED PROSPECTUS","category":"PROSPEKT","formatedDate":"02.11.2007"},{"message":"NORECO ANNOUNCES SALE OF ALTINEX RESERVOIR TECHNOLOGY AS","category":"AVTALER","formatedDate":"31.10.2007"},{"message":"MOTTATT SØKNAD OM BØRSNOTERING AV TO OBLIGASJONSLÅN","category":"NOTERING AV VERDIPAPIRE...","formatedDate":"29.10.2007"},{"message":"NORECO ANNOUNCES SALE OF ALTINEX SERVICES AS","category":"AVTALER","formatedDate":"26.10.2007"},{"message":"NORECO ACQUIRES TWO DANISH OFFSHORE LICENSES FROM CHEVRON DENMARK","category":"AVTALER","formatedDate":"25.10.2007"},{"message":"NORWEGIAN ENERGY COMPANY ASA","category":"ANDRE BØRSMELDINGER","formatedDate":"24.10.2007"},{"message":"NORWEGIAN ENERGY COMPANY ASA NOTERES PÅ OSLO BØRS","category":"ANDRE BØRSMELDINGER","formatedDate":"24.10.2007"},{"message":"REGISTERED SHARE CAPITAL INCREASE","category":"KAPITALENDRINGER / UTBY...","formatedDate":"23.10.2007"},{"message":"SHARE CAPITAL INCREASE","category":"KAPITALENDRINGER / UTBY...","formatedDate":"23.10.2007"},{"message":"NORECO SUCCESSFULLY COMPLETES NOK 550 MILLION PRIVATE PLACEMENT","category":"KAPITALENDRINGER / UTBY...","formatedDate":"22.10.2007"},{"message":"3RD QUARTER PRODUCTION","category":"ANDRE BØRSMELDINGER","formatedDate":"18.10.2007"},{"message":"NORECO - SHARE SPLIT","category":"ANDRE BØRSMELDINGER","formatedDate":"17.10.2007"},{"message":"SHARE SPLIT","category":"ANDRE BØRSMELDINGER","formatedDate":"16.10.2007"},{"message":"MINUTES FROM EXTRAORDINARY GENERAL MEETING","category":"GENERALFORSAMLINGSINFO","formatedDate":"10.10.2007"},{"message":"NORECO - NOMINATION OF DIRECTORS","category":"ANDRE BØRSMELDINGER","formatedDate":"08.10.2007"},{"message":"NORECO - COMPANY PRESENTATION","category":"ANDRE BØRSMELDINGER","formatedDate":"08.10.2007"},{"message":"NORECO - PRIVATE PLACEMENT OF UP TO NOK 700 MILLION","category":"ANDRE BØRSMELDINGER","formatedDate":"08.10.2007"},{"message":"NORECO ACQUIRES LICENSE ON NORWEGIAN CONTINENTAL SHELF","category":"AVTALER","formatedDate":"01.10.2007"},{"message":"CALLING NOTICE FOR EXTRAORDINARY GENERAL MEETING","category":"GENERALFORSAMLINGSINFO","formatedDate":"27.09.2007"},{"message":"INNKALLING TIL EKSTRAORDINÆR GENERALFORSAMLING","category":"GENERALFORSAMLINGSINFO","formatedDate":"27.09.2007"},{"message":"RECEIVED APPLICATION FOR LISTING","category":"SØKNAD","formatedDate":"27.09.2007"},{"message":"MOTTATT SØKNAD OM NOTERING","category":"SØKNAD","formatedDate":"27.09.2007"}]